Metadata-Version: 2.1
Name: cmake
Version: 3.28.4
Summary: CMake is an open-source, cross-platform family of tools designed to build, test and package software
Home-page: https://cmake.org/
Download-URL: https://cmake.org/download
Author: Jean-Christophe Fillion-Robin
Author-email: jchris.fillionr@kitware.com
License: Apache 2.0
Project-URL: Documentation, https://cmake-python-distributions.readthedocs.io/
Project-URL: Source Code, https://github.com/scikit-build/cmake-python-distributions
Project-URL: Mailing list, https://groups.google.com/forum/#!forum/scikit-build
Project-URL: Bug Tracker, https://github.com/scikit-build/cmake-python-distributions/issues
Keywords: CMake build c++ fortran cross-platform cross-compilation
Classifier: License :: OSI Approved :: Apache Software License
Classifier: License :: OSI Approved :: BSD License
Classifier: Programming Language :: C
Classifier: Programming Language :: C++
Classifier: Programming Language :: Fortran
Classifier: Programming Language :: Python
Classifier: Operating System :: OS Independent
Classifier: Development Status :: 5 - Production/Stable
Classifier: Intended Audience :: Developers
Classifier: Topic :: Software Development :: Build Tools
Classifier: Typing :: Typed
License-File: LICENSE_Apache_20
License-File: LICENSE_BSD_3
License-File: AUTHORS.rst
Provides-Extra: test
Requires-Dist: coverage>=4.2; extra == "test"
Requires-Dist: importlib_metadata>=2.0; extra == "test"
Requires-Dist: pytest>=3.0.3; extra == "test"
Requires-Dist: pytest-cov>=2.4.0; extra == "test"
